pymint/__init__.py
pymint/antlrgen/mint.interp
pymint/antlrgen/mint.tokens
pymint/antlrgen/mintLexer.interp
pymint/antlrgen/mintLexer.py
pymint/antlrgen/mintLexer.tokens
pymint/antlrgen/mintListener.py
pymint/antlrgen/mintParser.py
pymint/antlrgen/mintVisitor.py
pymint/cmdline.py
pymint/constraints/__init__.py
pymint/constraints/arrayconstraint.py
pymint/constraints/constraintlistener.py
pymint/constraints/layoutconstraint.py
pymint/constraints/lengthconstraint.py
pymint/constraints/mirrorconstraint.py
pymint/constraints/orientationconstraint.py
pymint/constraints/orthogonalconstraint.py
pymint/constraints/positionconstraint.py
pymint/constraints/rotationconstraint.py
pymint/mintErrorListener.py
pymint/mintcompiler.py
pymint/mintdevice.py
pymint/mintlayer.py
pymint/mintnode.py
pymint/mintprotocol.py
pymint/mintterminal.py
pymint/mintvia.py
pymint/mintwriter.py
pymint-0.3.3.dist-info/LICENSE.md
pymint-0.3.3.dist-info/METADATA
pymint-0.3.3.dist-info/WHEEL
pymint-0.3.3.dist-info/entry_points.txt
pymint-0.3.3.dist-info/RECORD
